{
	"Add":
	[		
	
		{
			"num_of_oprations":2,
			"numbers":[95626,54360],
			"Result":4,
			"status":"unsolved"
		},

		{ 
	
			"num_of_oprations":2,
			"numbers":[61850,41138],
			"Result":2,
			"status":"unsolved"
		},
		
		{
			"num_of_oprations":2,
			"numbers":[63323,15907],
			"Result":3,
			"status":"unsolved"
		},

		{
			"num_of_oprations":2,
			"numbers":[86417,84931],
			"Result":4,
			"status":"unsolved"
		},

		{	
			"num_of_oprations":2,
			"numbers":[58646,42206],
			"Result":1,
			"status":"unsolved"
		}                                
	]

}
