{
	"Add":
	[		
	
		{
			"num_of_oprations":4,
			"numbers":[99,-75,-21,64],
			"Result":4,
			"status":"unsolved"
		},

		{ 
	
			"num_of_oprations":4,
			"numbers":[97,-78,68,-23],
			"Result":2,
			"status":"unsolved"
		},
		
		{
			"num_of_oprations":4,
			"numbers":[88,-78,67,-48],
			"Result":3,
			"status":"unsolved"
		},

		{
			"num_of_oprations":4,
			"numbers":[91,-24,-36,43],
			"Result":4,
			"status":"unsolved"
		},

		{	
			"num_of_oprations":4,
			"numbers":[83,-28,11,-58],
			"Result":1,
			"status":"unsolved"
		},

		{
			"num_of_oprations":4,
			"numbers":[94,-49,-10,49],
			"Result":4,
			"status":"unsolved"
		},
			
		{
			"num_of_oprations":4,
			"numbers":[92,-13,-43,-18],
			"Result":3,
			"status":"unsolved"
		},

		{ 
	
			"num_of_oprations":4,
			"numbers":[83,-22,-48,88],
			"Result":4,
			"status":"unsolved"
		},
		{
			"num_of_oprations":4,
			"numbers":[76,-36,25,14],
			"Result":3,
			"status":"unsolved"
		},

		{	"num_of_oprations":4,
			"numbers":[75,-68,60,-53],
			"Result":3,
			"status":"unsolved"
		}		                                
	]

}
