{
	"Add":
	[		
	
		{
			"num_of_oprations":4,
			"numbers":[5,54,-3,-4],
			"Result":4,
			"status":"unsolved"
		},

		{ 
	
			"num_of_oprations":4,
			"numbers":[3,1,35,-2],
			"Result":2,
			"status":"unsolved"
		},
		
		{
			"num_of_oprations":4,
			"numbers":[75,-5,2,5],
			"Result":3,
			"status":"unsolved"
		},



		{	"num_of_oprations":4,
			"numbers":[4,1,41,1],
			"Result":2,
			"status":"unsolved"
		},


		{	"num_of_oprations":4,
			"numbers":[3,4,-4,23],
			"Result":2,
			"status":"unsolved"
		}

		

	]

}
