{
	"Mul":
	[		
	
		{
			"num_of_oprations":2,
			"numbers":[98,3],
			"Result":4,
			"status":"unsolved"
		},

		{ 
	
			"num_of_oprations":2,
			"numbers":[7,3],
			"Result":2,
			"status":"unsolved"
		},
		
		{
			"num_of_oprations":2,
			"numbers":[56,3],
			"Result":3,
			"status":"unsolved"
		},



		{	"num_of_oprations":2,
			"numbers":[21,3],
			"Result":2,
			"status":"unsolved"
		},


		{	"num_of_oprations":2,
			"numbers":[62,3],
			"Result":2,
			"status":"unsolved"
		},

		{	"num_of_oprations":2,
			"numbers":[53,3],
			"Result":2,
			"status":"unsolved"
		},

		{	"num_of_oprations":2,
			"numbers":[60,3],
			"Result":2,
			"status":"unsolved"
		},
		{	"num_of_oprations":2,
			"numbers":[17,3],
			"Result":2,
			"status":"unsolved"
		},
		{	"num_of_oprations":2,
			"numbers":[90,3],
			"Result":2,
			"status":"unsolved"
		},

		{	"num_of_oprations":2,
			"numbers":[13,3],
			"Result":2,
			"status":"unsolved"
		}

	]

}
