{
	"Add":
	[		
	
		{
			"num_of_oprations":8,
			"numbers":[69,39,60,-69,-55,30,56,-23],
			"Result":4,
			"status":"unsolved"
		},

		{ 
	
			"num_of_oprations":8,
			"numbers":[15,22,79,-51,75,13,-14,29],
			"Result":2,
			"status":"unsolved"
		},
		
		{
			"num_of_oprations":8,
			"numbers":[63,-25,34,21,96,22,63,-81],
			"Result":3,
			"status":"unsolved"
		},

		{
			"num_of_oprations":8,
			"numbers":[87,45,17,41,79,68,45,66],
			"Result":4,
			"status":"unsolved"
		},

		{	
			"num_of_oprations":8,
			"numbers":[10,73,20,86,35,-31,-82,80],
			"Result":1,
			"status":"unsolved"
		},
		                                
	]

}
