{
	"Add":
	[		
	
		{
			"num_of_oprations":4,
			"numbers":[45,15,-59,92],
			"Result":4,
			"status":"unsolved"
		},

		{ 
	
			"num_of_oprations":4,
			"numbers":[36,45,-28,-25],
			"Result":2,
			"status":"unsolved"
		},
		
		{
			"num_of_oprations":4,
			"numbers":[80,-32,-44,39],
			"Result":3,
			"status":"unsolved"
		},

		{
			"num_of_oprations":4,
			"numbers":[76,-27,-41,59],
			"Result":4,
			"status":"unsolved"
		},

		{	
			"num_of_oprations":4,
			"numbers":[25,56,-69,26],
			"Result":1,
			"status":"unsolved"
		},

		{
			"num_of_oprations":4,
			"numbers":[80,-51,-10,53],
			"Result":4,
			"status":"unsolved"
		},
			
		{
			"num_of_oprations":4,
			"numbers":[89,-79,42,36],
			"Result":3,
			"status":"unsolved"
		},

		{ 
	
			"num_of_oprations":4,
			"numbers":[83,11,-75,-14],
			"Result":4,
			"status":"unsolved"
		},
		{
			"num_of_oprations":4,
			"numbers":[81,-21,-55,74],
			"Result":3,
			"status":"unsolved"
		},

		{	"num_of_oprations":4,
			"numbers":[67,-34,61,-36],
			"Result":3,
			"status":"unsolved"
		},		                                
	]

}
