{
	"Add":
	[		
	
		{
			"num_of_oprations":7,
			"numbers":[51,74,12,86,34,-80,44],
			"Result":4,
			"status":"unsolved"
		},
		{ 
			"num_of_oprations":7,
			"numbers":[90,-56,-21,62,80,-87,44],
			"Result":2,
			"status":"unsolved"
		},
		{
			"num_of_oprations":7,
			"numbers":[16,40,78,-67,-45,65,64],
			"Result":3,
			"status":"unsolved"
		},
		{	"num_of_oprations":7,
			"numbers":[99,60,34,87,-27,19,26],
			"Result":2,
			"status":"unsolved"
		},
		{	"num_of_oprations":7,
			"numbers":[10,82,-73,86,18,33,94],
			"Result":2,
			"status":"unsolved"
		}

		

	]

}
