{
	"Add": [

		{
			"num_of_oprations":4,
			"numbers": [53,1,2,1],
			"Result": 2,
			"status": "unsolved"
		},
		{
			"num_of_oprations":4,
			"numbers": [18,-6,7,-4],
			"Result": 2,
			"status": "unsolved"
		},
		{
			"num_of_oprations":4,
			"numbers": [62,5,-3,1],
			"Result": 2,
			"status": "unsolved"
		},
		{
			"num_of_oprations":4,
			"numbers": [74,3,-4,2],
			"Result": 2,
			"status": "unsolved"
		},
		{
			"num_of_oprations":4,
			"numbers": [37,-2,4,-3],
			"Result": 2,
			"status": "unsolved"
		},
		{
			"num_of_oprations":4,
			"numbers": [54,-4,-1,5],
			"Result": 2,
			"status": "unsolved"
		},
		{
			"num_of_oprations":4,
			"numbers": [63,1,3,2],
			"Result": 2,
			"status": "unsolved"
		},
		{
			"num_of_oprations":4,
			"numbers": [24,1,-2,5],
			"Result": 2,
			"status": "unsolved"
		},
		{
			"num_of_oprations":4,
			"numbers": [56,-2,1,4],
			"Result": 2,
			"status": "unsolved"
		},
		{
			"num_of_oprations":4,
			"numbers": [81,4,-3,3],
			"Result": 2,
			"status": "unsolved"
		},





		{
			"num_of_oprations":4,
			"numbers": [34,1,1,2],
			"Result": 2,
			"status": "unsolved"
		},
		{
			"num_of_oprations":4,
			"numbers": [10,4,3,-5],
			"Result": 2,
			"status": "unsolved"
		},
		{
			"num_of_oprations":4,
			"numbers": [80,3,4,-6],
			"Result": 2,
			"status": "unsolved"
		},
		{
			"num_of_oprations":4,
			"numbers": [54,2,-5,7],
			"Result": 2,
			"status": "unsolved"
		},
		{
			"num_of_oprations":4,
			"numbers": [63,3,3,-8],
			"Result": 2,
			"status": "unsolved"
		},
		{
			"num_of_oprations":4,
			"numbers": [79,-5,1,2],
			"Result": 2,
			"status": "unsolved"
		},
		{
			"num_of_oprations":4,
			"numbers": [26,2,-7,4],
			"Result": 2,
			"status": "unsolved"
		},
		{
			"num_of_oprations":4,
			"numbers": [55,4,-6,3],
			"Result": 2,
			"status": "unsolved"
		},
		{
			"num_of_oprations":4,
			"numbers": [40,3,-1,4],
			"Result": 2,
			"status": "unsolved"
		},
		{
			"num_of_oprations":4,
			"numbers": [67,-6,4,3],
			"Result": 2,
			"status": "unsolved"
		},

		






		{
			"num_of_oprations":4,
			"numbers": [6,1,-1,-5],
			"Result": 2,
			"status": "unsolved"
		},
		{
			"num_of_oprations":4,
			"numbers": [4,5,-6,1],
			"Result": 2,
			"status": "unsolved"
		},
		{
			"num_of_oprations":4,
			"numbers": [6,2,1,-3],
			"Result": 2,
			"status": "unsolved"
		},
		{
			"num_of_oprations":4,
			"numbers": [6,-5,5,-1],
			"Result": 2,
			"status": "unsolved"
		},
		{
			"num_of_oprations":4,
			"numbers": [5,1,2,-3],
			"Result": 2,
			"status": "unsolved"
		},
		{
			"num_of_oprations":4,
			"numbers": [2,1,1,-3],
			"Result": 2,
			"status": "unsolved"
		},
		{
			"num_of_oprations":4,
			"numbers": [6,3,-5,-4],
			"Result": 2,
			"status": "unsolved"
		},
		{
			"num_of_oprations":4,
			"numbers": [4,5,-2,-1],
			"Result": 2,
			"status": "unsolved"
		},
		{
			"num_of_oprations":4,
			"numbers": [4,-4,1,5],
			"Result": 2,
			"status": "unsolved"
		},
		{
			"num_of_oprations":4,
			"numbers": [5,-5,1,3],
			"Result": 2,
			"status": "unsolved"
		}

	]

}
