{
	"Add":
	[		
	
		{
			"num_of_oprations":2,
			"numbers":[2645,2067],
			"Result":4,
			"status":"unsolved"
		},

		{ 
	
			"num_of_oprations":2,
			"numbers":[9588,9036],
			"Result":2,
			"status":"unsolved"
		},
		
		{
			"num_of_oprations":2,
			"numbers":[6490,5551],
			"Result":3,
			"status":"unsolved"
		},

		{
			"num_of_oprations":2,
			"numbers":[8092,7500],
			"Result":4,
			"status":"unsolved"
		},

		{	
			"num_of_oprations":2,
			"numbers":[9521,7326],
			"Result":1,
			"status":"unsolved"
		},

		{
			"num_of_oprations":2,
			"numbers":[4074,3094],
			"Result":4,
			"status":"unsolved"
		},

		{ 
	
			"num_of_oprations":2,
			"numbers":[7879,2093],
			"Result":2,
			"status":"unsolved"
		},
		
		{
			"num_of_oprations":2,
			"numbers":[7945,5404],
			"Result":3,
			"status":"unsolved"
		},

		{
			"num_of_oprations":2,
			"numbers":[9441,5791],
			"Result":4,
			"status":"unsolved"
		},

		{	
			"num_of_oprations":2,
			"numbers":[9120,8649],
			"Result":1,
			"status":"unsolved"
		}
	                                
	]

}
